cubicweb_counters/__init__.py
cubicweb_counters/__pkginfo__.py
cubicweb_counters/entities.py
cubicweb_counters/hooks.py
cubicweb_counters/schema.py
cubicweb_counters-0.6.0.dist-info/METADATA
cubicweb_counters-0.6.0.dist-info/WHEEL
cubicweb_counters-0.6.0.dist-info/entry_points.txt
cubicweb_counters-0.6.0.dist-info/top_level.txt
cubicweb_counters-0.6.0.dist-info/RECORD
