Metadata-Version: 2.1
Name: cubicweb-counters
Version: 0.6.0
Summary: sequence/counter classes
Home-page: https://forge.extranet.logilab.fr/cubicweb/cubes/cubicweb-counters
Author: LOGILAB S.A. (Paris, FRANCE)
Author-email: contact@logilab.fr
License: LGPL
Classifier: Environment :: Web Environment
Classifier: Framework :: CubicWeb
Classifier: Programming Language :: Python :: 3
Requires-Dist: cubicweb[postgresql]<5.0,>=4.0.0
